aesFileEncryptionManager/__init__.py
aesFileEncryptionManager/encryptionManager.py
aesFileEncryptionManager/file_decrypt.py
aesFileEncryptionManager/file_encrypt.py
aesFileEncryptionManager-1.0.5.dist-info/LICENSE.txt
aesFileEncryptionManager-1.0.5.dist-info/METADATA
aesFileEncryptionManager-1.0.5.dist-info/WHEEL
aesFileEncryptionManager-1.0.5.dist-info/entry_points.txt
aesFileEncryptionManager-1.0.5.dist-info/top_level.txt
aesFileEncryptionManager-1.0.5.dist-info/RECORD
