Metadata-Version: 2.2
Name: aesFileEncryptionManager
Version: 1.0.5
Summary: A simple encryption manager to encrypt and decrypt files using AES encryption.
Home-page: https://github.com/Zorba1973/aesFileEncryptionManager
Author: Zorba1973
Author-email: zorba1973@gmail.com
License-File: LICENSE.txt
Requires-Dist: pycryptodome>=3.21.0
Dynamic: author
Dynamic: author-email
Dynamic: description
Dynamic: description-content-type
Dynamic: home-page
Dynamic: requires-dist
Dynamic: summary
